pandoc_numbering/__init__.py
pandoc_numbering/_main.py
pandoc_numbering-3.5.0.0.dist-info/METADATA
pandoc_numbering-3.5.0.0.dist-info/WHEEL
pandoc_numbering-3.5.0.0.dist-info/entry_points.txt
pandoc_numbering-3.5.0.0.dist-info/licenses/LICENSE
pandoc_numbering-3.5.0.0.dist-info/RECORD
